pyCFOFiSAX/__init__.py
pyCFOFiSAX/_cfofisax.py
pyCFOFiSAX/_forest_iSAX.py
pyCFOFiSAX/_isax.py
pyCFOFiSAX/_node.py
pyCFOFiSAX/_tree_iSAX.py
pyCFOFiSAX/tests/__init__.py
pyCFOFiSAX/tests/iCFOF_Clust2_multitree.py
pyCFOFiSAX/tests/iCFOF_NAB_multitree.py
pyCFOFiSAX/tests/profiling.py
pyCFOFiSAX/tests/test_forest_iSAX.py
pyCFOFiSAX-0.1.0.dist-info/LICENSE
pyCFOFiSAX-0.1.0.dist-info/METADATA
pyCFOFiSAX-0.1.0.dist-info/WHEEL
pyCFOFiSAX-0.1.0.dist-info/top_level.txt
pyCFOFiSAX-0.1.0.dist-info/RECORD
