Metadata-Version: 2.1
Name: pyCFOFiSAX
Version: 0.1.0
Summary: Calculate CFOF score on stream context with iSAX trees
Home-page: https://gitlab.liris.cnrs.fr/lfoulon/icfof
Author: Lucas Foulon
Author-email: lucas.foulon@gmail.com
License: UNKNOWN
Platform: UNKNOWN
Classifier: Programming Language :: Python :: 3
Classifier: License :: OSI Approved :: MIT License
Classifier: Operating System :: OS Independent
Requires-Python: >=3.6
